{"generator":"phantomas v1.20.0","url":"http://localhost:8888/","metrics":{"requests":1,"gzipRequests":0,"postRequests":0,"httpsRequests":0,"notFound":0,"bodySize":9228,"contentLength":9228,"httpTrafficCompleted":334,"timeToFirstByte":297,"timeToLastByte":339,"ajaxRequests":0,"htmlCount":1,"htmlSize":9228,"cssCount":0,"cssSize":0,"jsCount":0,"jsSize":0,"jsonCount":0,"jsonSize":0,"imageCount":0,"imageSize":0,"videoCount":0,"videoSize":0,"webfontCount":0,"webfontSize":0,"base64Count":0,"base64Size":0,"otherCount":0,"otherSize":0,"cacheHits":0,"cacheMisses":0,"cachePasses":0,"cachingNotSpecified":0,"cachingTooShort":0,"cachingDisabled":0,"oldCachingHeaders":0,"cachingUseImmutable":0,"consoleMessages":0,"cookiesSent":0,"cookiesRecv":0,"domainsWithCookies":0,"documentCookiesLength":0,"documentCookiesCount":1,"documentHeight":1024,"commentsSize":0,"whiteSpacesSize":46,"DOMelementsCount":75,"DOMelementMaxDepth":5,"nodesWithInlineCSS":0,"imagesScaledDown":0,"imagesWithoutDimensions":0,"DOMidDuplicated":0,"hiddenContentSize":0,"hiddenImages":0,"DOMmutationsInserts":0,"DOMmutationsRemoves":0,"DOMmutationsAttributes":0,"DOMqueries":1,"DOMqueriesWithoutResults":0,"DOMqueriesById":1,"DOMqueriesByClassName":0,"DOMqueriesByTagName":0,"DOMqueriesByQuerySelectorAll":0,"DOMinserts":0,"DOMqueriesDuplicated":0,"DOMqueriesAvoidable":0,"domains":1,"maxRequestsPerDomain":1,"medianRequestsPerDomain":1,"eventsBound":2,"eventsDispatched":0,"eventsScrollBound":0,"globalVariables":8,"globalVariablesFalsy":0,"headersCount":7,"headersSentCount":2,"headersRecvCount":5,"headersSize":289,"headersSentSize":133,"headersRecvSize":156,"headersBiggerThanContent":0,"jQueryVersion":"","jQueryVersionsLoaded":0,"jQueryOnDOMReadyFunctions":0,"jQueryWindowOnLoadFunctions":0,"jQuerySizzleCalls":0,"jQueryEventTriggers":0,"jQueryDOMReads":0,"jQueryDOMWrites":0,"jQueryDOMWriteReadSwitches":0,"documentWriteCalls":0,"evalCalls":0,"jsErrors":0,"closedConnections":0,"lazyLoadableImagesBelowTheFold":0,"localStorageEntries":0,"redirects":0,"redirectsTime":0,"repaints":0,"firstPaint":0,"requestsToFirstPaint":0,"domainsToFirstPaint":0,"requestsToDomContentLoaded":1,"domainsToDomContentLoaded":1,"requestsToDomComplete":1,"domainsToDomComplete":1,"assetsNotGzipped":1,"assetsWithQueryString":0,"assetsWithCookies":0,"smallImages":0,"smallCssFiles":0,"smallJsFiles":0,"multipleRequests":0,"timeToFirstCss":0,"timeToFirstJs":0,"timeToFirstImage":0,"domInteractive":8,"domContentLoaded":353,"domContentLoadedEnd":10,"domComplete":11,"timeBackend":96,"timeFrontend":4,"requestsWithTimeout":0,"statusCodesTrail":"200","windowAlerts":0,"windowConfirms":0,"windowPrompts":0,"bodyHTMLSize":2554,"iframesCount":0,"smallestResponse":9228,"biggestResponse":9228,"fastestResponse":339,"slowestResponse":339,"smallestLatency":297,"biggestLatency":297,"medianResponse":339,"medianLatency":297},"offenders":{"htmlCount":["http://localhost:8888/ (size: 9.01 kB, latency: 297 ms)"],"DOMelementMaxDepth":["body > div#wrapper > ul#files > li[0] > a[0] > span.name","body > div#wrapper > ul#files > li[0] > a[0] > span.size","body > div#wrapper > ul#files > li[0] > a[0] > span.date","body > div#wrapper > ul#files > li[1] > a[0] > span.name","body > div#wrapper > ul#files > li[1] > a[0] > span.size","body > div#wrapper > ul#files > li[1] > a[0] > span.date","body > div#wrapper > ul#files > li[2] > a[0] > span.name","body > div#wrapper > ul#files > li[2] > a[0] > span.size","body > div#wrapper > ul#files > li[2] > a[0] > span.date","body > div#wrapper > ul#files > li[3] > a[0] > span.name","body > div#wrapper > ul#files > li[3] > a[0] > span.size","body > div#wrapper > ul#files > li[3] > a[0] > span.date","body > div#wrapper > ul#files > li[4] > a[0] > span.name","body > div#wrapper > ul#files > li[4] > a[0] > span.size","body > div#wrapper > ul#files > li[4] > a[0] > span.date","body > div#wrapper > ul#files > li[5] > a[0] > span.name","body > div#wrapper > ul#files > li[5] > a[0] > span.size","body > div#wrapper > ul#files > li[5] > a[0] > span.date","body > div#wrapper > ul#files > li[6] > a[0] > span.name","body > div#wrapper > ul#files > li[6] > a[0] > span.size","body > div#wrapper > ul#files > li[6] > a[0] > span.date","body > div#wrapper > ul#files > li[7] > a[0] > span.name","body > div#wrapper > ul#files > li[7] > a[0] > span.size","body > div#wrapper > ul#files > li[7] > a[0] > span.date","body > div#wrapper > ul#files > li[8] > a[0] > span.name","body > div#wrapper > ul#files > li[8] > a[0] > span.size","body > div#wrapper > ul#files > li[8] > a[0] > span.date","body > div#wrapper > ul#files > li[9] > a[0] > span.name","body > div#wrapper > ul#files > li[9] > a[0] > span.size","body > div#wrapper > ul#files > li[9] > a[0] > span.date","body > div#wrapper > ul#files > li[10] > a[0] > span.name","body > div#wrapper > ul#files > li[10] > a[0] > span.size","body > div#wrapper > ul#files > li[10] > a[0] > span.date","body > div#wrapper > ul#files > li[11] > a[0] > span.name","body > div#wrapper > ul#files > li[11] > a[0] > span.size","body > div#wrapper > ul#files > li[11] > a[0] > span.date","body > div#wrapper > ul#files > li[12] > a[0] > span.name","body > div#wrapper > ul#files > li[12] > a[0] > span.size","body > div#wrapper > ul#files > li[12] > a[0] > span.date","body > div#wrapper > ul#files > li[13] > a[0] > span.name","body > div#wrapper > ul#files > li[13] > a[0] > span.size","body > div#wrapper > ul#files > li[13] > a[0] > span.date"],"DOMqueriesById":["#search (in #document)"],"domains":["localhost: 1 request(s)"],"eventsBound":["\"DOMContentLoaded\" bound to \"window\"","\"keyup\" bound to \"body > input#search\""],"globalVariables":["$","search","on","all","each","getClasses","addClass","removeClass"],"domainsToDomContentLoaded":["localhost (1 requests)"],"domainsToDomComplete":["localhost (1 requests)"],"assetsNotGzipped":["http://localhost:8888/ (HTML)"],"smallestResponse":["http://localhost:8888/ (9.01 kB)"],"biggestResponse":["http://localhost:8888/ (9.01 kB)"],"fastestResponse":["http://localhost:8888/ (339 ms)"],"slowestResponse":["http://localhost:8888/ (339 ms)"],"smallestLatency":["http://localhost:8888/ (297 ms)"],"biggestLatency":["http://localhost:8888/ (297 ms)"]},"asserts":false}